scipystats666/__init__.py
scipystats666/q1.py
scipystats666-1.0.1.dist-info/LICENSE
scipystats666-1.0.1.dist-info/METADATA
scipystats666-1.0.1.dist-info/WHEEL
scipystats666-1.0.1.dist-info/top_level.txt
scipystats666-1.0.1.dist-info/RECORD
